nano-lib-py/__init__.py
nano-lib-py/_nbase32.cpython-39-darwin.so
nano-lib-py/_version.py
nano-lib-py/_work_ref.cpython-39-darwin.so
nano-lib-py/accounts.py
nano-lib-py/blocks.py
nano-lib-py/exceptions.py
nano-lib-py/units.py
nano-lib-py/util.py
nano-lib-py/work.py
nano_lib_py/__init__.py
nano_lib_py/_nbase32.cpython-39-darwin.so
nano_lib_py/_version.py
nano_lib_py/_work_ref.cpython-39-darwin.so
nano_lib_py/accounts.py
nano_lib_py/blocks.py
nano_lib_py/exceptions.py
nano_lib_py/units.py
nano_lib_py/util.py
nano_lib_py/work.py
nano_lib_py-0.5.4.dist-info/LICENSE
nano_lib_py-0.5.4.dist-info/METADATA
nano_lib_py-0.5.4.dist-info/WHEEL
nano_lib_py-0.5.4.dist-info/top_level.txt
nano_lib_py-0.5.4.dist-info/RECORD
