Metadata-Version: 2.1
Name: nano-lib-py
Version: 0.5.4
Summary: Forked Python library for working with the NANO cryptocurrency protocol
Home-page: https://github.com/gr0vity-dev/nano-lib-py
Author: Janne Pulkkinen
Author-email: jannepulk@gmail.com
License: CC0
Classifier: Programming Language :: Python
Classifier: Programming Language :: Python :: 3
Classifier: Programming Language :: Python :: 3.6
Classifier: Programming Language :: Python :: 3.7
Classifier: Programming Language :: Python :: 3.8
Classifier: Programming Language :: Python :: 3.9
Classifier: Programming Language :: Python :: 3.10
Classifier: Programming Language :: Python :: 3.11
Classifier: Programming Language :: Python :: 3.12
Classifier: Programming Language :: Python :: Implementation :: CPython
Classifier: Operating System :: Microsoft :: Windows
Classifier: Operating System :: POSIX :: Linux
Classifier: Topic :: Office/Business :: Financial
Requires-Python: >=3.6.0
License-File: LICENSE
Requires-Dist: py-ed25519-blake2b >=0.1.0
Requires-Dist: py-cpuinfo >=4
